minicpuset/ROM32K.v
module ROM32K(clock,address,out);
    input clock;
    input [14:0] address;
    output [15:0] out;

    reg [15:0] mem[32767:0];
    reg [15:0] out;

    always@(posedge clock)begin
        out <= mem[address];
    end

    integer i;
    initial begin
        for(i=0;i<32678;i++)
            mem[i] = 16'b0000000000000000;

        mem[0] = 16'b0000000000000000;
        mem[1] = 16'b1110111111010000;
        mem[2] = 16'b1110001100001000;
        mem[3] = 16'b1110011111010000;
        mem[4] = 16'b0000000000000001;
        mem[5] = 16'b1111110000010000;
        mem[6] = 16'b0000000000000010;
        mem[7] = 16'b1110001100001000;
    end
endmodule

minicpuset/ALU.v
module ALU(x,y,zx,nx,zy,ny,f,no,out,zr,ng);
    input [15:0] x,y;
    input zx,nx,zy,ny,f,no;
    output [15:0] out;
    output zr,ng;

    wire [15:0] w1,w2;
    wire [15:0] notw1,w3;
    wire [15:0] notw2,w4;
    wire [15:0] xandy,addxy,w5;
    wire [15:0] notw5;
    wire [15:0] outbuffer;
    wire [7:0] out0to7,out8to15;
    wire or0to7,or8to15,or0to15;
    
    assign w1 = (zx == 1'b0) ? x : 16'b0000000000000000;
    assign w2 = (zy == 1'b0) ? y : 16'b0000000000000000;

    assign notw1 = ~w1;
    assign w3 = (nx == 1'b0) ? w1 : notw1;

    assign notw2 = ~w2;
    assign w4 = (ny == 1'b0) ? w2 : notw2;

    assign xandy = w3 & w4;

    assign addxy = w3 + w4;
    assign w5 = (f == 1'b0) ? xandy : addxy;

    assign notw5 = ~w5;
    assign outbuffer = (no == 1'b0) ? w5 : notw5;

    assign out = outbuffer;

    assign out0to7 = outbuffer[7:0];
    assign out8to15 = outbuffer[15:8];
    assign ng = outbuffer[15];

    assign or0to7 = |out0to7;
    assign or8to15 = |out8to15;
    assign or0to15 = or0to7 | or8to15;
    assign zr = ~or0to15;
endmodule

minicpuset/Register.v
module Register(clock,in,load,out);
    input clock;
    input [15:0] in;
    input load;
    output [15:0] out;

    reg [15:0] out;

    always @(posedge clock) begin
            if(load == 1'b1) begin
                    out <= in;
            end else begin
                    out <= out;
            end     
    end
endmodule

minicpuset/pc.v
//プログラムカウンタ作るよ！！！！！！！！
module pc(in,inc,load,reset,out,clock);
    input [15:0] in;
    input load,reset,clock,inc;
    output [15:0] out;

    reg [15:0] out;

    initial begin
        out = 16'b0000000000000000;
    end

    always@(posedge clock) begin
        if(reset) begin
            out <= 16'b0000000000000000;
        end else if(load) begin
            out <= in;
        end else if(inc) begin
            out <= out + 16'b0000000000000001;
        end else begin
            out <= out;
        end
    end
endmodule

minicpuset/Mux16.v
module Mux16(in1,in2,sel,out);
    input [15:0] in1,in2;
    input sel;
    output [15:0] out;

    assign out = (sel == 0) ? in1 : in2;
endmodule

minicpuset/miniCPU.v
module miniCPU(inM,instruction,reset,outM,writeM,addressM,pc_,clock);
    input [15:0] inM,instruction;
    input reset,clock;
    output [15:0] outM;
    output writeM;
    output [14:0] addressM,pc_;

    wire h,o,j,n,i,e,p,q,k,l,u,v,m,w,s;
    wire [15:0] a,f,b1,g,c,pc_buf;

    assign h = instruction[15] & instruction[4];
    assign o = instruction[15] & instruction[5];
    assign j = instruction[15] & instruction[12];
    assign n = ~instruction[15];
    assign i = o | n;
    Mux16 Mux160(f,instruction,n,a);
    Register ARegister(clock,a,i,b1);
    assign addressM = b1[14:0];
    Mux16 Mux161(b1,inM,j,c);
    pc pc(b1,1'b1,e,reset,pc_buf,clock);
    assign pc_ = pc_buf[14:0];
    Register DRegister(clock,f,h,g);
    ALU ALU(g,c,instruction[11],instruction[10],instruction[9],instruction[8],instruction[7],instruction[6],outM,p,q);
    assign f = outM;
    assign k = p & instruction[1];
    assign l = q & instruction[2];
    assign u = p | q;
    assign v = ~u;
    assign m = k | l;
    assign w = v & instruction[0];
    assign s = w | m;
    assign e = s & instruction[15];
    assign writeM = instruction[3] & instruction[15];
endmodule

minicpuset/RAM32K.v
module RAM32K(clock,in,load,address,out);
    input clock,load;
    input [14:0] address;
    input [15:0] in;
    output [15:0] out;

    reg [15:0] mem[32767:0],out;

    //always @(posedge clock) begin
    //    if(load)begin
    //        mem[address] <= in;
    //        out <= out;
    //    end else begin
    //        out <= mem[address];
    //    end
    //end

    always @(posedge clock or address) begin
        if(load)begin
            mem[address] <= in;
            out <= out;
        end else begin
            out <= mem[address];
        end
    end

    integer i;
    initial begin
        for(i=0;i<32768;i++)
            mem[i] = 16'b0000000000000000;

        mem[0] = 16'b0000000000000000;
        mem[1] = 16'b0101010101010000;
    end

endmodule

minicpuset/Computer.v
module Computer(reset,clock);
    input reset,clock;
    wire writeM;
    wire [15:0] outM,inM,instruction;
    wire [14:0] addressM,pc_;

    RAM32K RAM32K(clock,outM,writeM,addressM,inM);
    miniCPU miniCPU(inM,instruction,reset,outM,writeM,addressM,pc_,clock);
    ROM32K ROM32K(clock,pc_,instruction);
endmodule

minicpuset/Simulation.v
module Simulation();
    reg reset;
    reg clock;

    initial begin
        $dumpfile("wave.vcd");
        $dumpvars(0,Computer,Computer.RAM32K.mem[0],Computer.RAM32K.mem[1],Computer.RAM32K.mem[2],Computer.RAM32K.mem[16]);
    end

    Computer Computer(reset,clock);

    initial begin
        reset = 1'b0;
        clock = 1'b0;
    end

    always #1 begin
        clock <= ~clock;
    end

    initial begin
        #100
        $finish;
    end
endmodule

minicpuset/dump.vcd
$date
	Mon May 20 00:35:51 2019
$end
$version
	Icarus Verilog
$end
$timescale
	1s
$end
$scope module Simulation $end
$scope module Computer $end
$scope module RAM32K $end
$var reg 16 ! \mem[0] [15:0] $end
$upscope $end
$upscope $end
$upscope $end
$scope module Simulation $end
$scope module Computer $end
$scope module RAM32K $end
$var reg 16 " \mem[1] [15:0] $end
$upscope $end
$upscope $end
$upscope $end
$scope module Simulation $end
$scope module Computer $end
$scope module RAM32K $end
$var reg 16 # \mem[2] [15:0] $end
$upscope $end
$upscope $end
$upscope $end
$scope module Simulation $end
$scope module Computer $end
$var wire 1 $ clock $end
$var wire 1 % reset $end
$var wire 1 & writeM $end
$var wire 15 ' pc_ [14:0] $end
$var wire 16 ( outM [15:0] $end
$var wire 16 ) instruction [15:0] $end
$var wire 16 * inM [15:0] $end
$var wire 15 + addressM [14:0] $end
$scope module RAM32K $end
$var wire 1 $ clock $end
$var wire 1 & load $end
$var wire 16 , in [15:0] $end
$var wire 15 - address [14:0] $end
$var reg 16 . out [15:0] $end
$var integer 32 / i [31:0] $end
$upscope $end
$scope module ROM32K $end
$var wire 1 $ clock $end
$var wire 15 0 address [14:0] $end
$var reg 16 1 out [15:0] $end
$var integer 32 2 i [31:0] $end
$upscope $end
$scope module miniCPU $end
$var wire 1 $ clock $end
$var wire 1 3 e $end
$var wire 16 4 f [15:0] $end
$var wire 1 5 h $end
$var wire 1 6 i $end
$var wire 16 7 inM [15:0] $end
$var wire 16 8 instruction [15:0] $end
$var wire 1 9 j $end
$var wire 1 : k $end
$var wire 1 ; l $end
$var wire 1 < m $end
$var wire 1 = n $end
$var wire 1 > o $end
$var wire 1 % reset $end
$var wire 1 ? s $end
$var wire 1 @ u $end
$var wire 1 A v $end
$var wire 1 B w $end
$var wire 1 & writeM $end
$var wire 1 C q $end
$var wire 16 D pc_buf [15:0] $end
$var wire 15 E pc_ [14:0] $end
$var wire 1 F p $end
$var wire 16 G outM [15:0] $end
$var wire 16 H g [15:0] $end
$var wire 16 I c [15:0] $end
$var wire 16 J b1 [15:0] $end
$var wire 15 K addressM [14:0] $end
$var wire 16 L a [15:0] $end
$scope module ALU $end
$var wire 1 M f $end
$var wire 1 N no $end
$var wire 16 O notw1 [15:0] $end
$var wire 16 P notw2 [15:0] $end
$var wire 16 Q notw5 [15:0] $end
$var wire 1 R nx $end
$var wire 1 S ny $end
$var wire 1 T or0to15 $end
$var wire 16 U out [15:0] $end
$var wire 16 V xandy [15:0] $end
$var wire 1 F zr $end
$var wire 1 W zx $end
$var wire 1 X zy $end
$var wire 16 Y y [15:0] $end
$var wire 16 Z x [15:0] $end
$var wire 16 [ w5 [15:0] $end
$var wire 16 \ w4 [15:0] $end
$var wire 16 ] w3 [15:0] $end
$var wire 16 ^ w2 [15:0] $end
$var wire 16 _ w1 [15:0] $end
$var wire 16 ` outbuffer [15:0] $end
$var wire 8 a out8to15 [7:0] $end
$var wire 8 b out0to7 [7:0] $end
$var wire 1 c or8to15 $end
$var wire 1 d or0to7 $end
$var wire 1 C ng $end
$var wire 16 e addxy [15:0] $end
$upscope $end
$scope module ARegister $end
$var wire 1 $ clock $end
$var wire 1 6 load $end
$var wire 16 f in [15:0] $end
$var reg 16 g out [15:0] $end
$upscope $end
$scope module DRegister $end
$var wire 1 $ clock $end
$var wire 16 h in [15:0] $end
$var wire 1 5 load $end
$var reg 16 i out [15:0] $end
$upscope $end
$scope module Mux160 $end
$var wire 16 j in1 [15:0] $end
$var wire 16 k in2 [15:0] $end
$var wire 1 = sel $end
$var wire 16 l out [15:0] $end
$upscope $end
$scope module Mux161 $end
$var wire 16 m in1 [15:0] $end
$var wire 16 n in2 [15:0] $end
$var wire 1 9 sel $end
$var wire 16 o out [15:0] $end
$upscope $end
$scope module pc $end
$var wire 1 $ clock $end
$var wire 16 p in [15:0] $end
$var wire 1 q inc $end
$var wire 1 3 load $end
$var wire 1 % reset $end
$var reg 16 r out [15:0] $end
$upscope $end
$upscope $end
$upscope $end
$upscope $end
$enddefinitions $end
#0
$dumpvars
bx r
1q
bx p
bx o
bx n
bx m
bx l
bx k
bx j
bx i
bx h
bx g
bx f
bx e
xd
xc
bx b
bx a
bx `
bx _
bx ^
bx ]
bx \
bx [
bx Z
bx Y
xX
xW
bx V
bx U
xT
xS
xR
bx Q
bx P
bx O
xN
xM
bx L
bx K
bx J
bx I
bx H
bx G
xF
bx E
bx D
xC
xB
xA
x@
x?
x>
x=
x<
x;
x:
x9
bx 8
bx 7
x6
x5
bx 4
x3
b111111110100110 2
bx 1
bx 0
b1000000000000000 /
bx .
bx -
bx ,
bx +
bx *
bx )
bx (
bx '
x&
1%
0$
b0 #
b0 "
b0 !
$end
#1
b0 '
b0 0
b0 E
b0 D
b0 r
1$
#2
0$
0%
#3
16
b10 L
b10 f
b10 l
05
0>
09
1=
0;
0B
03
0&
0W
0R
0X
0S
0M
0N
b1 '
b1 0
b1 E
b10 )
b10 1
b10 8
b10 k
b1 D
b1 r
1$
#4
0$
#5
b0x0 b
0c
b0 a
0C
b0x0 4
b0x0 h
b0x0 j
b0x0 (
b0x0 ,
b0x0 G
b0x0 U
b0x0 `
b11111111111111x1 Q
b0x0 [
b0x0 V
b10 \
b1111111111111101 P
b10 ^
b10 I
b10 Y
b10 o
b10 +
b10 -
b10 K
b10 '
b10 0
b10 E
b10 J
b10 g
b10 m
b10 p
b10 D
b10 r
1$
#6
0$
#7
0A
1@
1F
0T
0d
b0 V
b0 b
0c
b0 a
0C
b0 e
b0 ]
b1111111111111111 O
b0 \
b1111111111111111 P
b0 4
b0 h
b0 j
b0 (
b0 ,
b0 G
b0 U
b0 `
b1111111111111111 Q
0?
06
b0 _
b0 ^
b0 [
0<
0=
0:
03
1&
1W
1X
1M
b0 L
b0 f
b0 l
b11 '
b11 0
b11 E
b1110101010001000 )
b1110101010001000 1
b1110101010001000 8
b1110101010001000 k
b11 D
b11 r
b0 *
b0 .
b0 7
b0 n
1$
#8
0$
#9
xA
x@
xF
xT
xd
b0x0 b
b0x0 4
b0x0 h
b0x0 j
b0x0 (
b0x0 ,
b0x0 G
b0x0 U
b0x0 `
b11111111111111x1 Q
b0x0 [
b0x0 V
bx ]
bx O
bx e
b10 \
b1111111111111101 P
16
bx _
b10 ^
1=
0&
b100 '
b100 0
b100 E
0W
0X
0M
b0 #
b100 D
b100 r
b0 )
b0 1
b0 8
b0 k
1$
#10
0$
#11
0A
1@
1F
0T
0d
b0 b
b0 4
b0 h
b0 j
b0 (
b0 ,
b0 G
b0 U
b0 `
b1111111111111111 Q
b1111111111111111 e
b1111111111111111 ]
b0 [
b1111111111111111 O
b0 V
06
b0 _
b0 \
b1111111111111111 P
15
19
0=
b0 ^
1W
1R
b0 L
b0 f
b0 l
b101 '
b101 0
b101 E
b0 I
b0 Y
b0 o
b0 +
b0 -
b0 K
b1111110000010000 )
b1111110000010000 1
b1111110000010000 8
b1111110000010000 k
b101 D
b101 r
b0 J
b0 g
b0 m
b0 p
1$
#12
0$
#13
16
b10000 L
b10000 f
b10000 l
b0 e
b0 ]
05
09
1=
b110 '
b110 0
b110 E
0W
0R
b110 D
b110 r
b0 H
b0 Z
b0 i
b10000 )
b10000 1
b10000 8
b10000 k
1$
#14
0$
#15
06
b1111111111111111 e
b1111111111111111 \
b1111111111111111 P
0=
1&
b0 ^
1X
1S
b0 L
b0 f
b0 l
b111 '
b111 0
b111 E
b10000 I
b10000 Y
b10000 o
b10000 +
b10000 -
b10000 K
b1110001100001000 )
b1110001100001000 1
b1110001100001000 8
b1110001100001000 k
b111 D
b111 r
b10000 J
b10000 g
b10000 m
b10000 p
1$
#16
0$
#17
b1111111111101111 P
16
b10000 L
b10000 f
b10000 l
b10000 ^
b10000 e
b10000 \
1=
0&
b1000 '
b1000 0
b1000 E
0X
0S
b1000 D
b1000 r
b10000 )
b10000 1
b10000 8
b10000 k
1$
#18
0$
#19
0A
1@
1F
0T
0d
b0 b
b0 4
b0 h
b0 j
b0 (
b0 ,
b0 G
b0 U
b0 `
b1111111111111111 Q
b0 \
b1111111111111111 P
b0 [
b0 ^
b0 V
b0 I
b0 Y
b0 o
06
b1111111111111111 e
b1111111111111111 ]
15
19
0=
1W
1R
b0 L
b0 f
b0 l
b1001 '
b1001 0
b1001 E
b1111110000010000 )
b1111110000010000 1
b1111110000010000 8
b1111110000010000 k
b1001 D
b1001 r
1$
#20
0$
#21
0F
1T
1d
b11111111 b
1c
b11111111 a
1C
b1111111111111111 L
b1111111111111111 f
b1111111111111111 l
b1111111111111111 4
b1111111111111111 h
b1111111111111111 j
b1111111111111111 (
b1111111111111111 ,
b1111111111111111 G
b1111111111111111 U
b1111111111111111 `
b0 Q
b1111111111111111 [
05
1&
b1010 '
b1010 0
b1010 E
1M
b1010 D
b1010 r
b1111110010001000 )
b1111110010001000 1
b1111110010001000 8
b1111110010001000 k
1$
#22
0$
#23
0?
0B
1F
0A
0T
1@
b10000 \
b1111111111101111 P
0d
b0 b
0c
b0 a
0C
b10000 ^
b0 4
b0 h
b0 j
b0 (
b0 ,
b0 G
b0 U
b0 `
b1111111111111111 Q
b10000 I
b10000 Y
b10000 o
16
b10001 L
b10001 f
b10001 l
b10000 e
b0 ]
b0 [
09
1=
0&
0W
0R
0M
b1011 '
b1011 0
b1011 E
b10001 )
b10001 1
b10001 8
b10001 k
b1011 D
b1011 r
1$
#24
0$
#25
13
1?
b1111111111111111 P
06
b1111111111111111 e
b1111111111111111 \
1<
b0 ^
0=
1:
b10001 I
b10001 Y
b10001 o
b10001 +
b10001 -
b10001 K
b1100 '
b1100 0
b1100 E
1X
1S
b0 L
b0 f
b0 l
b1111111111111111 *
b1111111111111111 .
b1111111111111111 7
b1111111111111111 n
b10001 J
b10001 g
b10001 m
b10001 p
b1100 D
b1100 r
b1110001100000010 )
b1110001100000010 1
b1110001100000010 8
b1110001100000010 k
1$
#26
0$
#27
b1111111111101110 P
0?
16
b1 L
b1 f
b1 l
b10001 ^
b10001 e
b10001 \
0<
1=
0:
03
0X
0S
b10001 '
b10001 0
b10001 E
b1 )
b1 1
b1 8
b1 k
b10001 D
b10001 r
b0 *
b0 .
b0 7
b0 n
1$
#28
0$
#29
0B
0A
1@
1F
0T
0d
b0 b
13
b0 4
b0 h
b0 j
b0 (
b0 ,
b0 G
b0 U
b0 `
b1111111111111111 Q
1?
b0 e
b0 \
b1111111111111111 P
06
b0 [
1<
b0 ^
0=
1:
b1 I
b1 Y
b1 o
b1 +
b1 -
b1 K
b10010 '
b10010 0
b10010 E
1W
1X
1M
b0 L
b0 f
b0 l
b1 J
b1 g
b1 m
b1 p
b10010 D
b10010 r
b1110101010000111 )
b1110101010000111 1
b1110101010000111 8
b1110101010000111 k
1$
#30
0$
#31
b1 e
b1 \
b1111111111111110 P
0?
16
b10001 L
b10001 f
b10001 l
b1 ^
0<
1=
0:
03
0W
0X
0M
b1 '
b1 0
b1 E
b10001 )
b10001 1
b10001 8
b10001 k
b1 D
b1 r
1$
#32
0$
#33
1?
b10001 e
b10001 \
b1111111111101110 P
1<
b10001 ^
1:
b10001 I
b10001 Y
b10001 o
b10001 +
b10001 -
b10001 K
b10 '
b10 0
b10 E
b10 L
b10 f
b10 l
b10001 J
b10001 g
b10001 m
b10001 p
b10 D
b10 r
b10 )
b10 1
b10 8
b10 k
1$
#34
0$
#35
0A
1@
1F
0T
0d
b0 b
b0 4
b0 h
b0 j
b0 (
b0 ,
b0 G
b0 U
b0 `
b1111111111111111 Q
0?
06
b0 [
0<
b0 e
b0 \
b1111111111111111 P
0=
0:
03
1&
b0 ^
1W
1X
1M
b0 L
b0 f
b0 l
b11 '
b11 0
b11 E
b10 I
b10 Y
b10 o
b10 +
b10 -
b10 K
b1110101010001000 )
b1110101010001000 1
b1110101010001000 8
b1110101010001000 k
b11 D
b11 r
b10 J
b10 g
b10 m
b10 p
1$
#36
0$
#37
b10 e
b10 \
b1111111111111101 P
16
b10 ^
1=
0&
b100 '
b100 0
b100 E
0W
0X
0M
b0 #
b100 D
b100 r
b0 )
b0 1
b0 8
b0 k
1$
#38
0$
#39
06
b1111111111111111 ]
b1111111111111111 e
b0 \
b1111111111111111 P
15
19
0=
b0 ^
1W
1R
b0 L
b0 f
b0 l
b101 '
b101 0
b101 E
b0 I
b0 Y
b0 o
b0 +
b0 -
b0 K
b1111110000010000 )
b1111110000010000 1
b1111110000010000 8
b1111110000010000 k
b101 D
b101 r
b0 J
b0 g
b0 m
b0 p
1$
#40
0$
#41
16
b10000 L
b10000 f
b10000 l
b0 e
b0 ]
05
09
1=
b110 '
b110 0
b110 E
0W
0R
b110 D
b110 r
b10000 )
b10000 1
b10000 8
b10000 k
1$
#42
0$
#43
06
b1111111111111111 e
b1111111111111111 \
b1111111111111111 P
0=
1&
b0 ^
1X
1S
b0 L
b0 f
b0 l
b111 '
b111 0
b111 E
b10000 I
b10000 Y
b10000 o
b10000 +
b10000 -
b10000 K
b1110001100001000 )
b1110001100001000 1
b1110001100001000 8
b1110001100001000 k
b111 D
b111 r
b10000 J
b10000 g
b10000 m
b10000 p
1$
#44
0$
#45
b1111111111101111 P
16
b10000 L
b10000 f
b10000 l
b10000 ^
b10000 e
b10000 \
1=
0&
b1000 '
b1000 0
b1000 E
0X
0S
b1000 D
b1000 r
b10000 )
b10000 1
b10000 8
b10000 k
1$
#46
0$
#47
0A
1@
1F
0T
0d
b0 b
b0 4
b0 h
b0 j
b0 (
b0 ,
b0 G
b0 U
b0 `
b1111111111111111 Q
b0 \
b1111111111111111 P
b0 [
b0 ^
b0 V
b0 I
b0 Y
b0 o
06
b1111111111111111 e
b1111111111111111 ]
15
19
0=
1W
1R
b0 L
b0 f
b0 l
b1001 '
b1001 0
b1001 E
b1111110000010000 )
b1111110000010000 1
b1111110000010000 8
b1111110000010000 k
b1001 D
b1001 r
1$
#48
0$
#49
0F
1T
1d
b11111111 b
1c
b11111111 a
1C
b1111111111111111 L
b1111111111111111 f
b1111111111111111 l
b1111111111111111 4
b1111111111111111 h
b1111111111111111 j
b1111111111111111 (
b1111111111111111 ,
b1111111111111111 G
b1111111111111111 U
b1111111111111111 `
b0 Q
b1111111111111111 [
05
1&
b1010 '
b1010 0
b1010 E
1M
b1010 D
b1010 r
b1111110010001000 )
b1111110010001000 1
b1111110010001000 8
b1111110010001000 k
1$
#50
0$
#51
0?
0B
1F
0A
0T
1@
b10000 \
b1111111111101111 P
0d
b0 b
0c
b0 a
0C
b10000 ^
b0 4
b0 h
b0 j
b0 (
b0 ,
b0 G
b0 U
b0 `
b1111111111111111 Q
b10000 I
b10000 Y
b10000 o
16
b10001 L
b10001 f
b10001 l
b10000 e
b0 ]
b0 [
09
1=
0&
0W
0R
0M
b1011 '
b1011 0
b1011 E
b10001 )
b10001 1
b10001 8
b10001 k
b1011 D
b1011 r
1$
#52
0$
#53
13
1?
b1111111111111111 P
06
b1111111111111111 e
b1111111111111111 \
1<
b0 ^
0=
1:
b10001 I
b10001 Y
b10001 o
b10001 +
b10001 -
b10001 K
b1100 '
b1100 0
b1100 E
1X
1S
b0 L
b0 f
b0 l
b1111111111111111 *
b1111111111111111 .
b1111111111111111 7
b1111111111111111 n
b10001 J
b10001 g
b10001 m
b10001 p
b1100 D
b1100 r
b1110001100000010 )
b1110001100000010 1
b1110001100000010 8
b1110001100000010 k
1$
#54
0$
#55
b1111111111101110 P
0?
16
b1 L
b1 f
b1 l
b10001 ^
b10001 e
b10001 \
0<
1=
0:
03
0X
0S
b10001 '
b10001 0
b10001 E
b1 )
b1 1
b1 8
b1 k
b10001 D
b10001 r
b0 *
b0 .
b0 7
b0 n
1$
#56
0$
#57
0B
0A
1@
1F
0T
0d
b0 b
13
b0 4
b0 h
b0 j
b0 (
b0 ,
b0 G
b0 U
b0 `
b1111111111111111 Q
1?
b0 e
b0 \
b1111111111111111 P
06
b0 [
1<
b0 ^
0=
1:
b1 I
b1 Y
b1 o
b1 +
b1 -
b1 K
b10010 '
b10010 0
b10010 E
1W
1X
1M
b0 L
b0 f
b0 l
b1 J
b1 g
b1 m
b1 p
b10010 D
b10010 r
b1110101010000111 )
b1110101010000111 1
b1110101010000111 8
b1110101010000111 k
1$
#58
0$
#59
b1 e
b1 \
b1111111111111110 P
0?
16
b10001 L
b10001 f
b10001 l
b1 ^
0<
1=
0:
03
0W
0X
0M
b1 '
b1 0
b1 E
b10001 )
b10001 1
b10001 8
b10001 k
b1 D
b1 r
1$
#60
0$
#61
1?
b10001 e
b10001 \
b1111111111101110 P
1<
b10001 ^
1:
b10001 I
b10001 Y
b10001 o
b10001 +
b10001 -
b10001 K
b10 '
b10 0
b10 E
b10 L
b10 f
b10 l
b10001 J
b10001 g
b10001 m
b10001 p
b10 D
b10 r
b10 )
b10 1
b10 8
b10 k
1$
#62
0$
#63
0A
1@
1F
0T
0d
b0 b
b0 4
b0 h
b0 j
b0 (
b0 ,
b0 G
b0 U
b0 `
b1111111111111111 Q
0?
06
b0 [
0<
b0 e
b0 \
b1111111111111111 P
0=
0:
03
1&
b0 ^
1W
1X
1M
b0 L
b0 f
b0 l
b11 '
b11 0
b11 E
b10 I
b10 Y
b10 o
b10 +
b10 -
b10 K
b1110101010001000 )
b1110101010001000 1
b1110101010001000 8
b1110101010001000 k
b11 D
b11 r
b10 J
b10 g
b10 m
b10 p
1$
#64
0$
#65
b10 e
b10 \
b1111111111111101 P
16
b10 ^
1=
0&
b100 '
b100 0
b100 E
0W
0X
0M
b0 #
b100 D
b100 r
b0 )
b0 1
b0 8
b0 k
1$
#66
0$
#67
06
b1111111111111111 ]
b1111111111111111 e
b0 \
b1111111111111111 P
15
19
0=
b0 ^
1W
1R
b0 L
b0 f
b0 l
b101 '
b101 0
b101 E
b0 I
b0 Y
b0 o
b0 +
b0 -
b0 K
b1111110000010000 )
b1111110000010000 1
b1111110000010000 8
b1111110000010000 k
b101 D
b101 r
b0 J
b0 g
b0 m
b0 p
1$
#68
0$
#69
16
b10000 L
b10000 f
b10000 l
b0 e
b0 ]
05
09
1=
b110 '
b110 0
b110 E
0W
0R
b110 D
b110 r
b10000 )
b10000 1
b10000 8
b10000 k
1$
#70
0$
#71
06
b1111111111111111 e
b1111111111111111 \
b1111111111111111 P
0=
1&
b0 ^
1X
1S
b0 L
b0 f
b0 l
b111 '
b111 0
b111 E
b10000 I
b10000 Y
b10000 o
b10000 +
b10000 -
b10000 K
b1110001100001000 )
b1110001100001000 1
b1110001100001000 8
b1110001100001000 k
b111 D
b111 r
b10000 J
b10000 g
b10000 m
b10000 p
1$
#72
0$
#73
b1111111111101111 P
16
b10000 L
b10000 f
b10000 l
b10000 ^
b10000 e
b10000 \
1=
0&
b1000 '
b1000 0
b1000 E
0X
0S
b1000 D
b1000 r
b10000 )
b10000 1
b10000 8
b10000 k
1$
#74
0$
#75
0A
1@
1F
0T
0d
b0 b
b0 4
b0 h
b0 j
b0 (
b0 ,
b0 G
b0 U
b0 `
b1111111111111111 Q
b0 \
b1111111111111111 P
b0 [
b0 ^
b0 V
b0 I
b0 Y
b0 o
06
b1111111111111111 e
b1111111111111111 ]
15
19
0=
1W
1R
b0 L
b0 f
b0 l
b1001 '
b1001 0
b1001 E
b1111110000010000 )
b1111110000010000 1
b1111110000010000 8
b1111110000010000 k
b1001 D
b1001 r
1$
#76
0$
#77
0F
1T
1d
b11111111 b
1c
b11111111 a
1C
b1111111111111111 L
b1111111111111111 f
b1111111111111111 l
b1111111111111111 4
b1111111111111111 h
b1111111111111111 j
b1111111111111111 (
b1111111111111111 ,
b1111111111111111 G
b1111111111111111 U
b1111111111111111 `
b0 Q
b1111111111111111 [
05
1&
b1010 '
b1010 0
b1010 E
1M
b1010 D
b1010 r
b1111110010001000 )
b1111110010001000 1
b1111110010001000 8
b1111110010001000 k
1$
#78
0$
#79
0?
0B
1F
0A
0T
1@
b10000 \
b1111111111101111 P
0d
b0 b
0c
b0 a
0C
b10000 ^
b0 4
b0 h
b0 j
b0 (
b0 ,
b0 G
b0 U
b0 `
b1111111111111111 Q
b10000 I
b10000 Y
b10000 o
16
b10001 L
b10001 f
b10001 l
b10000 e
b0 ]
b0 [
09
1=
0&
0W
0R
0M
b1011 '
b1011 0
b1011 E
b10001 )
b10001 1
b10001 8
b10001 k
b1011 D
b1011 r
1$
#80
0$
#81
13
1?
b1111111111111111 P
06
b1111111111111111 e
b1111111111111111 \
1<
b0 ^
0=
1:
b10001 I
b10001 Y
b10001 o
b10001 +
b10001 -
b10001 K
b1100 '
b1100 0
b1100 E
1X
1S
b0 L
b0 f
b0 l
b1111111111111111 *
b1111111111111111 .
b1111111111111111 7
b1111111111111111 n
b10001 J
b10001 g
b10001 m
b10001 p
b1100 D
b1100 r
b1110001100000010 )
b1110001100000010 1
b1110001100000010 8
b1110001100000010 k
1$
#82
0$
#83
b1111111111101110 P
0?
16
b1 L
b1 f
b1 l
b10001 ^
b10001 e
b10001 \
0<
1=
0:
03
0X
0S
b10001 '
b10001 0
b10001 E
b1 )
b1 1
b1 8
b1 k
b10001 D
b10001 r
b0 *
b0 .
b0 7
b0 n
1$
#84
0$
#85
0B
0A
1@
1F
0T
0d
b0 b
13
b0 4
b0 h
b0 j
b0 (
b0 ,
b0 G
b0 U
b0 `
b1111111111111111 Q
1?
b0 e
b0 \
b1111111111111111 P
06
b0 [
1<
b0 ^
0=
1:
b1 I
b1 Y
b1 o
b1 +
b1 -
b1 K
b10010 '
b10010 0
b10010 E
1W
1X
1M
b0 L
b0 f
b0 l
b1 J
b1 g
b1 m
b1 p
b10010 D
b10010 r
b1110101010000111 )
b1110101010000111 1
b1110101010000111 8
b1110101010000111 k
1$
#86
0$
#87
b1 e
b1 \
b1111111111111110 P
0?
16
b10001 L
b10001 f
b10001 l
b1 ^
0<
1=
0:
03
0W
0X
0M
b1 '
b1 0
b1 E
b10001 )
b10001 1
b10001 8
b10001 k
b1 D
b1 r
1$
#88
0$
#89
1?
b10001 e
b10001 \
b1111111111101110 P
1<
b10001 ^
1:
b10001 I
b10001 Y
b10001 o
b10001 +
b10001 -
b10001 K
b10 '
b10 0
b10 E
b10 L
b10 f
b10 l
b10001 J
b10001 g
b10001 m
b10001 p
b10 D
b10 r
b10 )
b10 1
b10 8
b10 k
1$
#90
0$
#91
0A
1@
1F
0T
0d
b0 b
b0 4
b0 h
b0 j
b0 (
b0 ,
b0 G
b0 U
b0 `
b1111111111111111 Q
0?
06
b0 [
0<
b0 e
b0 \
b1111111111111111 P
0=
0:
03
1&
b0 ^
1W
1X
1M
b0 L
b0 f
b0 l
b11 '
b11 0
b11 E
b10 I
b10 Y
b10 o
b10 +
b10 -
b10 K
b1110101010001000 )
b1110101010001000 1
b1110101010001000 8
b1110101010001000 k
b11 D
b11 r
b10 J
b10 g
b10 m
b10 p
1$
#92
0$
#93
b10 e
b10 \
b1111111111111101 P
16
b10 ^
1=
0&
b100 '
b100 0
b100 E
0W
0X
0M
b0 #
b100 D
b100 r
b0 )
b0 1
b0 8
b0 k
1$
#94
0$
#95
06
b1111111111111111 ]
b1111111111111111 e
b0 \
b1111111111111111 P
15
19
0=
b0 ^
1W
1R
b0 L
b0 f
b0 l
b101 '
b101 0
b101 E
b0 I
b0 Y
b0 o
b0 +
b0 -
b0 K
b1111110000010000 )
b1111110000010000 1
b1111110000010000 8
b1111110000010000 k
b101 D
b101 r
b0 J
b0 g
b0 m
b0 p
1$
#96
0$
#97
16
b10000 L
b10000 f
b10000 l
b0 e
b0 ]
05
09
1=
b110 '
b110 0
b110 E
0W
0R
b110 D
b110 r
b10000 )
b10000 1
b10000 8
b10000 k
1$
#98
0$
#99
06
b1111111111111111 e
b1111111111111111 \
b1111111111111111 P
0=
1&
b0 ^
1X
1S
b0 L
b0 f
b0 l
b111 '
b111 0
b111 E
b10000 I
b10000 Y
b10000 o
b10000 +
b10000 -
b10000 K
b1110001100001000 )
b1110001100001000 1
b1110001100001000 8
b1110001100001000 k
b111 D
b111 r
b10000 J
b10000 g
b10000 m
b10000 p
1$
#100
0$
#101
b1111111111101111 P
16
b10000 L
b10000 f
b10000 l
b10000 ^
b10000 e
b10000 \
1=
0&
b1000 '
b1000 0
b1000 E
0X
0S
b1000 D
b1000 r
b10000 )
b10000 1
b10000 8
b10000 k
1$
#102
0$
