minicpuset/pc.v
//プログラムカウンタ作るよ！！！！！！！！
module pc(in,inc,load,reset,out,clock);
    input [15:0] in;
    input load,reset,clock,inc;
    output [15:0] out;

    reg [15:0] out;

    initial begin
        out = 16'b0000000000000000;
    end

    always@(posedge clock) begin
        if(reset) begin
            out <= 16'b0000000000000000;
        end else if(load) begin
            out <= in;
        end else if(inc) begin
            out <= out + 16'b0000000000000001;
        end else begin
            out <= out;
        end
    end
endmodule

minicpuset/pcsim.v
module pcsim();
    reg [15:0] in;
    reg load,reset,clock,inc;
    wire [15:0] out;

    initial begin
        clock <= 1'b0;
    end

    always #1 begin
        clock <= ~clock;
    end

    pc pc(in,inc,load,reset,out,clock);

    initial begin
        $dumpfile("pcwave.vcd");
        $dumpvars(0,pc);
    end

    initial begin
        reset <= 1'b1;
        inc <= 1'b1;
        #2
        reset <= 1'b0;
        #100
        $finish;
    end
endmodule

minicpuset/pcwave.vcd
$date
	Tue May 21 21:13:30 2019
$end
$version
	Icarus Verilog
$end
$timescale
	1s
$end
$scope module pcsim $end
$scope module pc $end
$var wire 1 ! clock $end
$var wire 16 " in [15:0] $end
$var wire 1 # inc $end
$var wire 1 $ load $end
$var wire 1 % reset $end
$var reg 16 & out [15:0] $end
$upscope $end
$upscope $end
$enddefinitions $end
#0
$dumpvars
bx &
1%
x$
1#
bx "
0!
$end
#1
b0 &
1!
#2
0!
0%
#3
b1 &
1!
#4
0!
#5
b10 &
1!
#6
0!
#7
b11 &
1!
#8
0!
#9
b100 &
1!
#10
0!
#11
b101 &
1!
#12
0!
#13
b110 &
1!
#14
0!
#15
b111 &
1!
#16
0!
#17
b1000 &
1!
#18
0!
#19
b1001 &
1!
#20
0!
#21
b1010 &
1!
#22
0!
#23
b1011 &
1!
#24
0!
#25
b1100 &
1!
#26
0!
#27
b1101 &
1!
#28
0!
#29
b1110 &
1!
#30
0!
#31
b1111 &
1!
#32
0!
#33
b10000 &
1!
#34
0!
#35
b10001 &
1!
#36
0!
#37
b10010 &
1!
#38
0!
#39
b10011 &
1!
#40
0!
#41
b10100 &
1!
#42
0!
#43
b10101 &
1!
#44
0!
#45
b10110 &
1!
#46
0!
#47
b10111 &
1!
#48
0!
#49
b11000 &
1!
#50
0!
#51
b11001 &
1!
#52
0!
#53
b11010 &
1!
#54
0!
#55
b11011 &
1!
#56
0!
#57
b11100 &
1!
#58
0!
#59
b11101 &
1!
#60
0!
#61
b11110 &
1!
#62
0!
#63
b11111 &
1!
#64
0!
#65
b100000 &
1!
#66
0!
#67
b100001 &
1!
#68
0!
#69
b100010 &
1!
#70
0!
#71
b100011 &
1!
#72
0!
#73
b100100 &
1!
#74
0!
#75
b100101 &
1!
#76
0!
#77
b100110 &
1!
#78
0!
#79
b100111 &
1!
#80
0!
#81
b101000 &
1!
#82
0!
#83
b101001 &
1!
#84
0!
#85
b101010 &
1!
#86
0!
#87
b101011 &
1!
#88
0!
#89
b101100 &
1!
#90
0!
#91
b101101 &
1!
#92
0!
#93
b101110 &
1!
#94
0!
#95
b101111 &
1!
#96
0!
#97
b110000 &
1!
#98
0!
#99
b110001 &
1!
#100
0!
#101
b110010 &
1!
