minicpuset/ROM32K.v
module ROM32K(clock,address,out);
    input clock;
    input [14:0] address;
    output [15:0] out;

    reg [15:0] mem[32767:0];
    wire [15:0] out;

    assign out = mem[address];

    integer i;
    initial begin
        for(i=0;i<32678;i++)
            mem[i] = 16'b0000000000000000;

        mem[0] = 16'b0000000000000010;
        mem[1] = 16'b1110101010001000;
        mem[2] = 16'b0000000000000000;
        mem[3] = 16'b1111110000010000;
        mem[4] = 16'b0000000000010000;
        mem[5] = 16'b1110001100001000;
        mem[6] = 16'b0000000000010000;
        mem[7] = 16'b1111110000010000;
        mem[8] = 16'b1111110010001000;
        mem[9] = 16'b0000000000010001;
        mem[10] = 16'b1110001100000010;
        mem[11] = 16'b0000000000000001;
        mem[12] = 16'b1111110000010000;
        mem[13] = 16'b0000000000000010;
        mem[14] = 16'b1111000010001000;
        mem[15] = 16'b0000000000000110;
        mem[16] = 16'b1110101010000111;
        mem[17] = 16'b0000000000010001;
        mem[18] = 16'b1110101010000111;
    end
endmodule

minicpuset/ALU.v
module ALU(x,y,zx,nx,zy,ny,f,no,out,zr,ng);
    input [15:0] x,y;
    input zx,nx,zy,ny,f,no;
    output [15:0] out;
    output zr,ng;

    wire [15:0] w1,w2;
    wire [15:0] notw1,w3;
    wire [15:0] notw2,w4;
    wire [15:0] xandy,addxy,w5;
    wire [15:0] notw5;
    wire [15:0] outbuffer;
    wire [7:0] out0to7,out8to15;
    wire or0to7,or8to15,or0to15;
    
    assign w1 = (zx == 1'b0) ? x : 16'b0000000000000000;
    assign w2 = (zy == 1'b0) ? y : 16'b0000000000000000;

    assign notw1 = ~w1;
    assign w3 = (nx == 1'b0) ? w1 : notw1;

    assign notw2 = ~w2;
    assign w4 = (ny == 1'b0) ? w2 : notw2;

    assign xandy = w3 & w4;

    assign addxy = w3 + w4;
    assign w5 = (f == 1'b0) ? xandy : addxy;

    assign notw5 = ~w5;
    assign outbuffer = (no == 1'b0) ? w5 : notw5;

    assign out = outbuffer;

    assign out0to7 = outbuffer[7:0];
    assign out8to15 = outbuffer[15:8];
    assign ng = outbuffer[15];

    assign or0to7 = |out0to7;
    assign or8to15 = |out8to15;
    assign or0to15 = or0to7 | or8to15;
    assign zr = ~or0to15;
endmodule

minicpuset/Register.v
module Register(clock,in,load,out);
    input clock;
    input [15:0] in;
    input load;
    output [15:0] out;

    reg [15:0] out;

    always @(posedge clock) begin
            if(load == 1'b1) begin
                    out <= in;
            end else begin
                    out <= out;
            end     
    end
endmodule

minicpuset/pc.v
//プログラムカウンタ作るよ！！！！！！！！
module pc(in,inc,load,reset,out,clock);
    input [15:0] in;
    input load,reset,clock,inc;
    output [15:0] out;

    reg [15:0] out;

    initial begin
        out = 16'b0000000000000000;
    end

    always@(posedge clock) begin
        if(reset) begin
            out <= 16'b0000000000000000;
        end else if(load) begin
            out <= in;
        end else if(inc) begin
            out <= out + 16'b0000000000000001;
        end else begin
            out <= out;
        end
    end
endmodule

minicpuset/Mux16.v
module Mux16(in1,in2,sel,out);
    input [15:0] in1,in2;
    input sel;
    output [15:0] out;

    assign out = (sel == 0) ? in1 : in2;
endmodule

minicpuset/miniCPU.v
module miniCPU(inM,instruction,reset,outM,writeM,addressM,pc_,clock);
    input [15:0] inM,instruction;
    input reset,clock;
    output [15:0] outM;
    output writeM;
    output [14:0] addressM,pc_;

    wire h,o,j,n,i,e,p,q,k,l,u,v,m,w,s;
    wire [15:0] a,f,b1,g,c,pc_buf;

    assign h = instruction[15] & instruction[4];
    assign o = instruction[15] & instruction[5];
    assign j = instruction[15] & instruction[12];
    assign n = ~instruction[15];
    assign i = o | n;
    Mux16 Mux160(f,instruction,n,a);
    Register ARegister(clock,a,i,b1);
    assign addressM = b1[14:0];
    Mux16 Mux161(b1,inM,j,c);
    pc pc(b1,1'b1,e,reset,pc_buf,clock);
    assign pc_ = pc_buf[14:0];
    Register DRegister(clock,f,h,g);
    ALU ALU(g,c,instruction[11],instruction[10],instruction[9],instruction[8],instruction[7],instruction[6],outM,p,q);
    assign f = outM;
    assign k = p & instruction[1];
    assign l = q & instruction[2];
    assign u = p | q;
    assign v = ~u;
    assign m = k | l;
    assign w = v & instruction[0];
    assign s = w | m;
    assign e = s & instruction[15];
    assign writeM = instruction[3] & instruction[15];
endmodule

minicpuset/RAM32K.v
module RAM32K(clock,in,load,address,out);
    input clock,load;
    input [14:0] address;
    input [15:0] in;
    output [15:0] out;

    reg [15:0] mem[32767:0];
    wire [15:0] out;

    //always @(posedge clock) begin
    //    if(load)begin
    //        mem[address] <= in;
    //        out <= out;
    //    end else begin
    //        out <= mem[address];
    //    end
    //end

    always @(posedge clock or address)
        if(load) mem[address] <= in;

    assign out = mem[address];

    integer i;
    initial begin
        for(i=0;i<32768;i++)
            mem[i] = 16'b0000000000000000;

        mem[0] = 16'b0000000000000011;
        mem[1] = 16'b0000000000010011;
    end

endmodule

minicpuset/Computer.v
module Computer(reset,clock);
    input reset,clock;
    wire writeM;
    wire [15:0] outM,inM,instruction;
    wire [14:0] addressM,pc_;


    RAM32K RAM32K(clock,outM,writeM,addressM,inM);
    miniCPU miniCPU(inM,instruction,reset,outM,writeM,addressM,pc_,clock);
    ROM32K ROM32K(clock,pc_,instruciton);
endmodule

minicpuset/Simulation.v
module Simulation();
    reg reset;
    reg clock;

    initial begin
        $dumpfile("wave.vcd");
        $dumpvars(0,Computer,Computer.RAM32K.mem[0],Computer.RAM32K.mem[1],Computer.RAM32K.mem[2],Computer.RAM32K.mem[16]);
    end

    Computer Computer(reset,clock);

    initial begin
        reset = 1'b0;
        clock = 1'b0;
    end

    always #1 begin
        clock <= ~clock;
    end

    initial begin
        #500
        $finish;
    end
endmodule

minicpuset/wave.vcd
$date
	Thu May 23 02:20:24 2019
$end
$version
	Icarus Verilog
$end
$timescale
	1s
$end
$scope module Simulation $end
$scope module Computer $end
$var wire 1 ! clock $end
$var wire 1 " reset $end
$var wire 1 # writeM $end
$var wire 15 $ pc_ [14:0] $end
$var wire 16 % outM [15:0] $end
$var wire 16 & instruction [15:0] $end
$var wire 16 ' inM [15:0] $end
$var wire 15 ( addressM [14:0] $end
$scope module RAM32K $end
$var wire 1 ! clock $end
$var wire 16 ) out [15:0] $end
$var wire 1 # load $end
$var wire 16 * in [15:0] $end
$var wire 15 + address [14:0] $end
$var integer 32 , i [31:0] $end
$upscope $end
$scope module ROM32K $end
$var wire 1 ! clock $end
$var wire 16 - out [15:0] $end
$var wire 15 . address [14:0] $end
$var integer 32 / i [31:0] $end
$upscope $end
$scope module miniCPU $end
$var wire 1 ! clock $end
$var wire 1 0 e $end
$var wire 16 1 f [15:0] $end
$var wire 1 2 h $end
$var wire 1 3 i $end
$var wire 16 4 inM [15:0] $end
$var wire 16 5 instruction [15:0] $end
$var wire 1 6 j $end
$var wire 1 7 k $end
$var wire 1 8 l $end
$var wire 1 9 m $end
$var wire 1 : n $end
$var wire 1 ; o $end
$var wire 1 " reset $end
$var wire 1 < s $end
$var wire 1 = u $end
$var wire 1 > v $end
$var wire 1 ? w $end
$var wire 1 # writeM $end
$var wire 1 @ q $end
$var wire 16 A pc_buf [15:0] $end
$var wire 15 B pc_ [14:0] $end
$var wire 1 C p $end
$var wire 16 D outM [15:0] $end
$var wire 16 E g [15:0] $end
$var wire 16 F c [15:0] $end
$var wire 16 G b1 [15:0] $end
$var wire 15 H addressM [14:0] $end
$var wire 16 I a [15:0] $end
$scope module ALU $end
$var wire 1 J f $end
$var wire 1 K no $end
$var wire 16 L notw1 [15:0] $end
$var wire 16 M notw2 [15:0] $end
$var wire 16 N notw5 [15:0] $end
$var wire 1 O nx $end
$var wire 1 P ny $end
$var wire 1 Q or0to15 $end
$var wire 16 R out [15:0] $end
$var wire 16 S xandy [15:0] $end
$var wire 1 C zr $end
$var wire 1 T zx $end
$var wire 1 U zy $end
$var wire 16 V y [15:0] $end
$var wire 16 W x [15:0] $end
$var wire 16 X w5 [15:0] $end
$var wire 16 Y w4 [15:0] $end
$var wire 16 Z w3 [15:0] $end
$var wire 16 [ w2 [15:0] $end
$var wire 16 \ w1 [15:0] $end
$var wire 16 ] outbuffer [15:0] $end
$var wire 8 ^ out8to15 [7:0] $end
$var wire 8 _ out0to7 [7:0] $end
$var wire 1 ` or8to15 $end
$var wire 1 a or0to7 $end
$var wire 1 @ ng $end
$var wire 16 b addxy [15:0] $end
$upscope $end
$scope module ARegister $end
$var wire 1 ! clock $end
$var wire 1 3 load $end
$var wire 16 c in [15:0] $end
$var reg 16 d out [15:0] $end
$upscope $end
$scope module DRegister $end
$var wire 1 ! clock $end
$var wire 16 e in [15:0] $end
$var wire 1 2 load $end
$var reg 16 f out [15:0] $end
$upscope $end
$scope module Mux160 $end
$var wire 16 g in1 [15:0] $end
$var wire 16 h in2 [15:0] $end
$var wire 1 : sel $end
$var wire 16 i out [15:0] $end
$upscope $end
$scope module Mux161 $end
$var wire 16 j in1 [15:0] $end
$var wire 16 k in2 [15:0] $end
$var wire 1 6 sel $end
$var wire 16 l out [15:0] $end
$upscope $end
$scope module pc $end
$var wire 1 ! clock $end
$var wire 16 m in [15:0] $end
$var wire 1 n inc $end
$var wire 1 0 load $end
$var wire 1 " reset $end
$var reg 16 o out [15:0] $end
$upscope $end
$upscope $end
$upscope $end
$upscope $end
$scope module Simulation $end
$scope module Computer $end
$scope module RAM32K $end
$var reg 16 p \mem[0] [15:0] $end
$upscope $end
$upscope $end
$upscope $end
$scope module Simulation $end
$scope module Computer $end
$scope module RAM32K $end
$var reg 16 q \mem[1] [15:0] $end
$upscope $end
$upscope $end
$upscope $end
$scope module Simulation $end
$scope module Computer $end
$scope module RAM32K $end
$var reg 16 r \mem[2] [15:0] $end
$upscope $end
$upscope $end
$upscope $end
$scope module Simulation $end
$scope module Computer $end
$scope module RAM32K $end
$var reg 16 s \mem[16] [15:0] $end
$upscope $end
$upscope $end
$upscope $end
$enddefinitions $end
#0
$dumpvars
b0 s
b0 r
b10011 q
b11 p
b0 o
1n
bx m
bx l
bx k
bx j
b10 i
b10 h
bx g
bx f
bx e
bx d
b10 c
bx b
xa
x`
bx _
bx ^
bx ]
bx \
bx [
bx Z
bx Y
bx X
bx W
bx V
0U
0T
bx S
bx R
xQ
0P
0O
bx N
bx M
bx L
0K
0J
b10 I
bx H
bx G
bx F
bx E
bx D
xC
b0 B
b0 A
x@
0?
x>
x=
x<
0;
1:
x9
08
x7
06
b10 5
bx 4
13
02
bx 1
00
b111111110100110 /
b0 .
b10 -
b1000000000000000 ,
bx +
bx *
bx )
bx (
bx '
b10 &
bx %
b0 $
0#
0"
0!
$end
#1
0>
1=
1C
0Q
0a
b0 _
0`
b0 ^
0@
b0 1
b0 e
b0 g
b0 %
b0 *
b0 D
b0 R
b0 ]
b1111111111111111 N
b0 X
b0 b
b0 Z
b1111111111111111 L
0<
b0 S
03
b0 \
09
b0 Y
b1111111111111111 M
0:
07
00
1#
b0 [
1T
1U
1J
b0 I
b0 c
b0 i
b10 F
b10 V
b10 l
b0 '
b0 )
b0 4
b0 k
b10 (
b10 +
b10 H
b1110101010001000 &
b1110101010001000 -
b1110101010001000 5
b1110101010001000 h
b1 $
b1 .
b1 B
b10 G
b10 d
b10 j
b10 m
b1 A
b1 o
1!
#2
0!
#3
x>
x=
xC
xQ
xa
b0x0 _
b0x0 1
b0x0 e
b0x0 g
b0x0 %
b0x0 *
b0x0 D
b0x0 R
b0x0 ]
b11111111111111x1 N
b0x0 X
b0x0 S
bx Z
bx L
bx b
b10 Y
b1111111111111101 M
13
bx \
b10 [
1:
0#
0T
0U
0J
b0 &
b0 -
b0 5
b0 h
b10 $
b10 .
b10 B
b0 r
b10 A
b10 o
1!
#4
0!
#5
1>
0=
0C
1Q
1a
b11 _
b11 1
b11 e
b11 g
b11 %
b11 *
b11 D
b11 R
b11 ]
b1111111111111100 N
b10 b
b1111111111111111 Z
b11 X
b1111111111111111 L
b11 S
03
b0 \
b11 Y
b1111111111111100 M
12
16
0:
b11 [
1T
1O
b11 I
b11 c
b11 i
b11 F
b11 V
b11 l
b11 '
b11 )
b11 4
b11 k
b0 (
b0 +
b0 H
b1111110000010000 &
b1111110000010000 -
b1111110000010000 5
b1111110000010000 h
b11 $
b11 .
b11 B
b0 G
b0 d
b0 j
b0 m
b11 A
b11 o
1!
#6
0!
#7
0>
1=
1C
0Q
0a
b0 _
b0 1
b0 e
b0 g
b0 %
b0 *
b0 D
b0 R
b0 ]
b1111111111111111 N
b0 Y
b1111111111111111 M
b0 X
b0 [
b1111111111111100 L
b0 S
b0 F
b0 V
b0 l
13
b10000 I
b10000 c
b10000 i
b11 \
b11 b
b11 Z
02
06
1:
0T
0O
b10000 &
b10000 -
b10000 5
b10000 h
b100 $
b100 .
b100 B
b11 E
b11 W
b11 f
b100 A
b100 o
1!
#8
0!
#9
1>
0=
0C
1Q
1a
b11 _
b11 1
b11 e
b11 g
b11 %
b11 *
b11 D
b11 R
b11 ]
b1111111111111100 N
b11 X
b11 S
03
b10 b
b1111111111111111 Y
b1111111111111111 M
0:
1#
b0 [
1U
1P
b11 I
b11 c
b11 i
b10000 F
b10000 V
b10000 l
b0 '
b0 )
b0 4
b0 k
b10000 (
b10000 +
b10000 H
b1110001100001000 &
b1110001100001000 -
b1110001100001000 5
b1110001100001000 h
b101 $
b101 .
b101 B
b10000 G
b10000 d
b10000 j
b10000 m
b101 A
b101 o
1!
#10
0!
#11
0>
1=
1C
0Q
0a
b0 _
b0 1
b0 e
b0 g
b0 %
b0 *
b0 D
b0 R
b0 ]
b1111111111111111 N
b0 X
b1111111111101111 M
b0 S
13
b10000 I
b10000 c
b10000 i
b10000 [
b10011 b
b10000 Y
1:
0#
0U
0P
b10000 &
b10000 -
b10000 5
b10000 h
b110 $
b110 .
b110 B
b11 s
b11 '
b11 )
b11 4
b11 k
b110 A
b110 o
1!
#12
0!
#13
1>
0=
0C
1Q
1a
b11 _
b11 1
b11 e
b11 g
b11 %
b11 *
b11 D
b11 R
b11 ]
b1111111111111100 N
b11 Y
b1111111111111100 M
b11 X
b11 [
b1111111111111111 L
b11 S
b11 F
b11 V
b11 l
03
b0 \
b10 b
b1111111111111111 Z
12
16
0:
1T
1O
b11 I
b11 c
b11 i
b1111110000010000 &
b1111110000010000 -
b1111110000010000 5
b1111110000010000 h
b111 $
b111 .
b111 B
b111 A
b111 o
1!
#14
0!
#15
b10 _
b10 I
b10 c
b10 i
b10 1
b10 e
b10 g
b10 %
b10 *
b10 D
b10 R
b10 ]
b1111111111111101 N
b10 X
02
1#
1J
b1111110010001000 &
b1111110010001000 -
b1111110010001000 5
b1111110010001000 h
b1000 $
b1000 .
b1000 B
b1000 A
b1000 o
1!
#16
0!
#17
0>
1=
1C
0Q
0a
b0 _
b1111111111111100 L
b0 1
b0 e
b0 g
b0 %
b0 *
b0 D
b0 R
b0 ]
b1111111111111111 N
b0 S
13
b10001 I
b10001 c
b10001 i
b11 \
b11 Z
b0 X
0<
b10011 b
b10000 Y
b1111111111101111 M
06
1:
0?
0#
b10000 [
0T
0O
0J
b10000 F
b10000 V
b10000 l
b10001 &
b10001 -
b10001 5
b10001 h
b1001 $
b1001 .
b1001 B
b10 s
b10 '
b10 )
b10 4
b10 k
b1001 A
b1001 o
1!
#18
0!
#19
1>
0=
0C
1Q
1a
b11 _
00
b11 1
b11 e
b11 g
b11 %
b11 *
b11 D
b11 R
b11 ]
b1111111111111100 N
0<
b11 X
03
09
b11 S
0:
07
b10 b
b1111111111111111 Y
b1111111111111111 M
1U
1P
b11 I
b11 c
b11 i
b0 [
b1110001100000010 &
b1110001100000010 -
b1110001100000010 5
b1110001100000010 h
b1010 $
b1010 .
b1010 B
b10001 F
b10001 V
b10001 l
b0 '
b0 )
b0 4
b0 k
b10001 (
b10001 +
b10001 H
b1010 A
b1010 o
b10001 G
b10001 d
b10001 j
b10001 m
1!
#20
0!
#21
1>
0=
0C
1Q
1a
b1 _
b1 1
b1 e
b1 g
b1 %
b1 *
b1 D
b1 R
b1 ]
b1111111111111110 N
b1 X
b1111111111101110 M
b1 S
13
b1 I
b1 c
b1 i
b10001 [
b10100 b
b10001 Y
1<
1:
1?
0U
0P
b1 &
b1 -
b1 5
b1 h
b1011 $
b1011 .
b1011 B
b1011 A
b1011 o
1!
#22
0!
#23
1>
0=
0C
1Q
1a
b10011 _
b10011 1
b10011 e
b10011 g
b10011 %
b10011 *
b10011 D
b10011 R
b10011 ]
b1111111111101100 N
b10011 X
b1111111111111111 L
b10011 S
03
b0 \
b1111111111111111 Z
0<
12
16
0:
0?
00
b10010 b
b10011 Y
b1111111111101100 M
1T
1O
b10011 I
b10011 c
b10011 i
b10011 [
b1111110000010000 &
b1111110000010000 -
b1111110000010000 5
b1111110000010000 h
b1100 $
b1100 .
b1100 B
b10011 F
b10011 V
b10011 l
b10011 '
b10011 )
b10011 4
b10011 k
b1 (
b1 +
b1 H
b1100 A
b1100 o
b1 G
b1 d
b1 j
b1 m
1!
#24
0!
#25
0<
1>
09
0=
07
0C
1Q
1a
b1 _
b1 1
b1 e
b1 g
b1 %
b1 *
b1 D
b1 R
b1 ]
b1111111111111110 N
b1 Y
b1111111111111110 M
b1 X
b1 [
b1111111111101100 L
b1 S
b1 F
b1 V
b1 l
13
b10 I
b10 c
b10 i
b10011 \
b10100 b
b10011 Z
02
06
1:
0T
0O
b10 &
b10 -
b10 5
b10 h
b1101 $
b1101 .
b1101 B
b1101 A
b1101 o
b10011 E
b10011 W
b10011 f
1!
#26
0!
#27
b10011 _
b10011 1
b10011 e
b10011 g
b10011 %
b10011 *
b10011 D
b10011 R
b10011 ]
b1111111111101100 N
03
b10011 X
b0 S
16
0:
1#
b10011 b
b0 Y
b1111111111111111 M
1J
b10011 I
b10011 c
b10011 i
b0 [
b1111000010001000 &
b1111000010001000 -
b1111000010001000 5
b1111000010001000 h
b1110 $
b1110 .
b1110 B
b0 F
b0 V
b0 l
b0 '
b0 )
b0 4
b0 k
b10 (
b10 +
b10 H
b1110 A
b1110 o
b10 G
b10 d
b10 j
b10 m
1!
#28
0!
#29
0<
1>
09
0=
07
0C
1Q
1a
b10 _
b10 1
b10 e
b10 g
b10 %
b10 *
b10 D
b10 R
b10 ]
b1111111111111101 N
b10 S
13
b110 I
b110 c
b110 i
b10 X
b10101 b
b10 Y
b1111111111111101 M
06
1:
0#
b10 [
0J
b10 F
b10 V
b10 l
b110 &
b110 -
b110 5
b110 h
b1111 $
b1111 .
b1111 B
b10011 r
b10011 '
b10011 )
b10011 4
b10011 k
b1111 A
b1111 o
1!
#30
0!
#31
0>
19
1=
17
1C
0Q
0a
b0 S
b0 _
b0 Z
b1111111111111111 L
b0 1
b0 e
b0 g
b0 %
b0 *
b0 D
b0 R
b0 ]
b1111111111111111 N
10
03
b0 \
b0 X
1<
0:
0?
b0 b
b0 Y
b1111111111111111 M
1T
1U
1J
b0 I
b0 c
b0 i
b0 [
b1110101010000111 &
b1110101010000111 -
b1110101010000111 5
b1110101010000111 h
b10000 $
b10000 .
b10000 B
b110 F
b110 V
b110 l
b0 '
b0 )
b0 4
b0 k
b110 (
b110 +
b110 H
b10000 A
b10000 o
b110 G
b110 d
b110 j
b110 m
1!
#32
0!
#33
1>
0=
0C
1Q
1a
b10 _
b10 1
b10 e
b10 g
b10 %
b10 *
b10 D
b10 R
b10 ]
b1111111111111101 N
b10 X
b10 S
b10011 Z
b1111111111101100 L
b11001 b
b110 Y
b1111111111111001 M
0<
13
b10000 I
b10000 c
b10000 i
b10011 \
b110 [
09
1:
07
00
0T
0U
0J
b10000 &
b10000 -
b10000 5
b10000 h
b110 $
b110 .
b110 B
b110 A
b110 o
1!
#34
0!
#35
1>
0=
0C
1Q
1a
b10 _
b10 1
b10 e
b10 g
b10 %
b10 *
b10 D
b10 R
b10 ]
b1111111111111101 N
b1111111111111111 L
b10 X
03
b0 \
b1111111111111111 Z
b10 S
12
16
0:
b1 b
b10 Y
b1111111111111101 M
1T
1O
b10 I
b10 c
b10 i
b10 [
b1111110000010000 &
b1111110000010000 -
b1111110000010000 5
b1111110000010000 h
b111 $
b111 .
b111 B
b10 F
b10 V
b10 l
b10 '
b10 )
b10 4
b10 k
b10000 (
b10000 +
b10000 H
b111 A
b111 o
b10000 G
b10000 d
b10000 j
b10000 m
1!
#36
0!
#37
b1 _
b1 I
b1 c
b1 i
b1 1
b1 e
b1 g
b1 %
b1 *
b1 D
b1 R
b1 ]
b1111111111111110 N
b1 X
02
1#
1J
b1111110010001000 &
b1111110010001000 -
b1111110010001000 5
b1111110010001000 h
b1000 $
b1000 .
b1000 B
b1000 A
b1000 o
b10 E
b10 W
b10 f
1!
#38
0!
#39
0>
1=
1C
0Q
0a
b0 _
b1111111111111101 L
b0 1
b0 e
b0 g
b0 %
b0 *
b0 D
b0 R
b0 ]
b1111111111111111 N
b0 S
13
b10001 I
b10001 c
b10001 i
b10 \
b10 Z
b0 X
0<
b10010 b
b10000 Y
b1111111111101111 M
06
1:
0?
0#
b10000 [
0T
0O
0J
b10000 F
b10000 V
b10000 l
b10001 &
b10001 -
b10001 5
b10001 h
b1001 $
b1001 .
b1001 B
b1 s
b1 '
b1 )
b1 4
b1 k
b1001 A
b1001 o
1!
#40
0!
#41
1>
0=
0C
1Q
1a
b10 _
b10 1
b10 e
b10 g
b10 %
b10 *
b10 D
b10 R
b10 ]
b1111111111111101 N
00
b10 X
0<
b10 S
03
09
b1 b
b1111111111111111 Y
b1111111111111111 M
0:
07
b0 [
1U
1P
b10 I
b10 c
b10 i
b10001 F
b10001 V
b10001 l
b0 '
b0 )
b0 4
b0 k
b10001 (
b10001 +
b10001 H
b1110001100000010 &
b1110001100000010 -
b1110001100000010 5
b1110001100000010 h
b1010 $
b1010 .
b1010 B
b10001 G
b10001 d
b10001 j
b10001 m
b1010 A
b1010 o
1!
#42
0!
#43
0>
1=
1C
0Q
0a
b0 _
b0 1
b0 e
b0 g
b0 %
b0 *
b0 D
b0 R
b0 ]
b1111111111111111 N
b0 X
b1111111111101110 M
b0 S
13
b1 I
b1 c
b1 i
b10001 [
b10011 b
b10001 Y
0<
1:
0?
0U
0P
b1 &
b1 -
b1 5
b1 h
b1011 $
b1011 .
b1011 B
b1011 A
b1011 o
1!
#44
0!
#45
1>
0=
0C
1Q
1a
b10011 _
b10011 1
b10011 e
b10011 g
b10011 %
b10011 *
b10011 D
b10011 R
b10011 ]
b1111111111101100 N
b10011 X
b1111111111111111 L
b10011 S
03
b0 \
b1111111111111111 Z
b10010 b
b10011 Y
b1111111111101100 M
12
16
0:
b10011 [
1T
1O
b10011 I
b10011 c
b10011 i
b10011 F
b10011 V
b10011 l
b10011 '
b10011 )
b10011 4
b10011 k
b1 (
b1 +
b1 H
b1111110000010000 &
b1111110000010000 -
b1111110000010000 5
b1111110000010000 h
b1100 $
b1100 .
b1100 B
b1 G
b1 d
b1 j
b1 m
b1100 A
b1100 o
1!
#46
0!
#47
0<
1>
09
0=
07
0C
1Q
1a
b1 _
b1 1
b1 e
b1 g
b1 %
b1 *
b1 D
b1 R
b1 ]
b1111111111111110 N
b1 Y
b1111111111111110 M
b1 X
b1 [
b1111111111101100 L
b1 S
b1 F
b1 V
b1 l
13
b10 I
b10 c
b10 i
b10011 \
b10100 b
b10011 Z
02
06
1:
0T
0O
b10 &
b10 -
b10 5
b10 h
b1101 $
b1101 .
b1101 B
b10011 E
b10011 W
b10011 f
b1101 A
b1101 o
1!
#48
0!
#49
b100110 _
b100110 1
b100110 e
b100110 g
b100110 %
b100110 *
b100110 D
b100110 R
b100110 ]
b1111111111011001 N
b10011 S
03
b100110 X
b100110 b
b10011 Y
b1111111111101100 M
16
0:
1#
b10011 [
1J
b100110 I
b100110 c
b100110 i
b10011 F
b10011 V
b10011 l
b10 (
b10 +
b10 H
b1111000010001000 &
b1111000010001000 -
b1111000010001000 5
b1111000010001000 h
b1110 $
b1110 .
b1110 B
b10 G
b10 d
b10 j
b10 m
b1110 A
b1110 o
1!
#50
0!
#51
b10 _
b10 1
b10 e
b10 g
b10 %
b10 *
b10 D
b10 R
b10 ]
b1111111111111101 N
b10 S
13
b110 I
b110 c
b110 i
b10 X
b10101 b
b10 Y
b1111111111111101 M
06
1:
0#
b10 [
0J
b10 F
b10 V
b10 l
b110 &
b110 -
b110 5
b110 h
b1111 $
b1111 .
b1111 B
b100110 r
b100110 '
b100110 )
b100110 4
b100110 k
b1111 A
b1111 o
1!
#52
0!
#53
0>
19
1=
17
1C
0Q
0a
b0 S
b0 _
b0 Z
b1111111111111111 L
b0 1
b0 e
b0 g
b0 %
b0 *
b0 D
b0 R
b0 ]
b1111111111111111 N
10
03
b0 \
b0 X
1<
b0 b
b0 Y
b1111111111111111 M
0:
0?
b0 [
1T
1U
1J
b0 I
b0 c
b0 i
b110 F
b110 V
b110 l
b0 '
b0 )
b0 4
b0 k
b110 (
b110 +
b110 H
b1110101010000111 &
b1110101010000111 -
b1110101010000111 5
b1110101010000111 h
b10000 $
b10000 .
b10000 B
b110 G
b110 d
b110 j
b110 m
b10000 A
b10000 o
1!
#54
0!
#55
1>
0=
0C
1Q
1a
b10 _
b10 1
b10 e
b10 g
b10 %
b10 *
b10 D
b10 R
b10 ]
b1111111111111101 N
b10 X
b10 S
b10011 Z
b1111111111101100 L
b11001 b
b110 Y
b1111111111111001 M
0<
13
b10000 I
b10000 c
b10000 i
b10011 \
b110 [
09
1:
07
00
0T
0U
0J
b10000 &
b10000 -
b10000 5
b10000 h
b110 $
b110 .
b110 B
b110 A
b110 o
1!
#56
0!
#57
1>
0=
0C
1Q
1a
b1 _
b1 1
b1 e
b1 g
b1 %
b1 *
b1 D
b1 R
b1 ]
b1111111111111110 N
b1 X
b1111111111111111 L
b1 S
03
b0 \
b1111111111111111 Z
b0 b
b1 Y
b1111111111111110 M
12
16
0:
b1 [
1T
1O
b1 I
b1 c
b1 i
b1 F
b1 V
b1 l
b1 '
b1 )
b1 4
b1 k
b10000 (
b10000 +
b10000 H
b1111110000010000 &
b1111110000010000 -
b1111110000010000 5
b1111110000010000 h
b111 $
b111 .
b111 B
b10000 G
b10000 d
b10000 j
b10000 m
b111 A
b111 o
1!
#58
0!
#59
0>
1=
1C
0Q
0a
b0 _
b0 I
b0 c
b0 i
b0 1
b0 e
b0 g
b0 %
b0 *
b0 D
b0 R
b0 ]
b1111111111111111 N
b0 X
02
1#
1J
b1111110010001000 &
b1111110010001000 -
b1111110010001000 5
b1111110010001000 h
b1000 $
b1000 .
b1000 B
b1 E
b1 W
b1 f
b1000 A
b1000 o
1!
#60
0!
#61
0<
0?
0>
1=
1C
0Q
0a
b0 _
b1111111111111110 L
b0 1
b0 e
b0 g
b0 %
b0 *
b0 D
b0 R
b0 ]
b1111111111111111 N
b0 S
13
b10001 I
b10001 c
b10001 i
b1 \
b1 Z
b0 X
b10001 b
b10000 Y
b1111111111101111 M
06
1:
0#
b10000 [
0T
0O
0J
b10000 F
b10000 V
b10000 l
b10001 &
b10001 -
b10001 5
b10001 h
b1001 $
b1001 .
b1001 B
b0 s
b0 '
b0 )
b0 4
b0 k
b1001 A
b1001 o
1!
#62
0!
#63
1>
0=
0C
1Q
1a
b1 _
00
b1 1
b1 e
b1 g
b1 %
b1 *
b1 D
b1 R
b1 ]
b1111111111111110 N
0<
b1 X
03
09
b1 S
0:
07
b0 b
b1111111111111111 Y
b1111111111111111 M
1U
1P
b1 I
b1 c
b1 i
b0 [
b1110001100000010 &
b1110001100000010 -
b1110001100000010 5
b1110001100000010 h
b1010 $
b1010 .
b1010 B
b10001 F
b10001 V
b10001 l
b10001 (
b10001 +
b10001 H
b1010 A
b1010 o
b10001 G
b10001 d
b10001 j
b10001 m
1!
#64
0!
#65
1>
0=
0C
1Q
1a
b1 _
b1 1
b1 e
b1 g
b1 %
b1 *
b1 D
b1 R
b1 ]
b1111111111111110 N
b1 X
b1111111111101110 M
b1 S
13
b10001 [
b10010 b
b10001 Y
1<
1:
1?
0U
0P
b1 &
b1 -
b1 5
b1 h
b1011 $
b1011 .
b1011 B
b1011 A
b1011 o
1!
#66
0!
#67
1>
0=
0C
1Q
1a
b10011 _
b10011 1
b10011 e
b10011 g
b10011 %
b10011 *
b10011 D
b10011 R
b10011 ]
b1111111111101100 N
b10011 X
b1111111111111111 L
b10011 S
03
b0 \
b1111111111111111 Z
0<
12
16
0:
0?
00
b10010 b
b10011 Y
b1111111111101100 M
1T
1O
b10011 I
b10011 c
b10011 i
b10011 [
b1111110000010000 &
b1111110000010000 -
b1111110000010000 5
b1111110000010000 h
b1100 $
b1100 .
b1100 B
b10011 F
b10011 V
b10011 l
b10011 '
b10011 )
b10011 4
b10011 k
b1 (
b1 +
b1 H
b1100 A
b1100 o
b1 G
b1 d
b1 j
b1 m
1!
#68
0!
#69
0<
1>
09
0=
07
0C
1Q
1a
b1 _
b1 1
b1 e
b1 g
b1 %
b1 *
b1 D
b1 R
b1 ]
b1111111111111110 N
b1 Y
b1111111111111110 M
b1 X
b1 [
b1111111111101100 L
b1 S
b1 F
b1 V
b1 l
13
b10 I
b10 c
b10 i
b10011 \
b10100 b
b10011 Z
02
06
1:
0T
0O
b10 &
b10 -
b10 5
b10 h
b1101 $
b1101 .
b1101 B
b1101 A
b1101 o
b10011 E
b10011 W
b10011 f
1!
#70
0!
